scripts-1.0.1.data/scripts/pycclean
scripts-1.0.1.data/scripts/myip
scripts-1.0.1.data/scripts/apt-add-key
scripts-1.0.1.dist-info/RECORD
scripts-1.0.1.dist-info/top_level.txt
scripts-1.0.1.dist-info/entry_points.txt
scripts-1.0.1.dist-info/metadata.json
scripts-1.0.1.dist-info/METADATA
scripts-1.0.1.dist-info/WHEEL
scripts-1.0.1.dist-info/DESCRIPTION.rst
scripts/cdriso.py
scripts/cdblank.py
scripts/my_backup.py
scripts/unpkg.py
scripts/__init__.py
scripts/pg_backup.py
scripts/pkg.py
scripts/apt.py
scripts/cdwrite.py
