Metadata-Version: 2.0
Name: scripts
Version: 1.0.1
Summary: Various shell scripts
Requires-Dist: stua
